{
    "Cars": [
        {
            "id": "25186179",
            "mark": "Mercedes-Benz",
            "model": "Mercedes-Benz Междугородный",
            "issue": 2012,
            "eng_volume": 2.2,
            "color": "Белый",
            "body_type": "Междугородный",
            "milage": 412000,
            "price": 17000.0
        },
        {
            "id": "25196840",
            "mark": "Mercedes-Benz",
            "model": "Mercedes-Benz Пригородный",
            "issue": 2000,
            "eng_volume": 3.0,
            "color": "Белый",
            "body_type": "Пригородный",
            "milage": 415000,
            "price": 7500.0
        },
        {
            "id": "25211505",
            "mark": "Mercedes-Benz",
            "model": "Mercedes-Benz Междугородный",
            "issue": 2003,
            "eng_volume": 2.2,
            "color": "Серебристый",
            "body_type": "Междугородный",
            "milage": 417000,
            "price": 7500.0
        },
        {
            "id": "25224795",
            "mark": "Mercedes-Benz",
            "model": "Mercedes-Benz Междугородный",
            "issue": 2005,
            "eng_volume": 2.2,
            "color": "Серебристый",
            "body_type": "Междугородный",
            "milage": 325000,
            "price": 13500.0
        },
        {
            "id": "25240208",
            "mark": "Mercedes-Benz",
            "model": "Mercedes-Benz Междугородный",
            "issue": 2011,
            "eng_volume": 2.2,
            "color": "Белый",
            "body_type": "Междугородный",
            "milage": "Не указано",
            "price": 15172.0
        },
        {
            "id": "25250938",
            "mark": "Mercedes-Benz",
            "model": "Mercedes-Benz Городской",
            "issue": 1991,
            "eng_volume": 3.0,
            "color": "Белый",
            "body_type": "Городской",
            "milage": 317000,
            "price": 4248.0
        },
        {
            "id": "25266796",
            "mark": "Mercedes-Benz",
            "model": "Mercedes-Benz Туристический",
            "issue": 2003,
            "eng_volume": 2.2,
            "color": "Белый",
            "body_type": "Туристический",
            "milage": "Не указано",
            "price": 12800.0
        },
        {
            "id": "25281421",
            "mark": "Mercedes-Benz",
            "model": "Mercedes-Benz Туристический",
            "issue": 2005,
            "eng_volume": 2.2,
            "color": "Белый",
            "body_type": "Туристический",
            "milage": "Не указано",
            "price": 8496.0
        },
        {
            "id": "25296483",
            "mark": "Setra",
            "model": "Setra Top Class",
            "issue": 1984,
            "eng_volume": 4.0,
            "color": "Жёлтый",
            "body_type": "Туристический",
            "milage": "Не указано",
            "price": 10000.0
        },
        {
            "id": "25311257",
            "mark": "Scania",
            "model": "Scania Туристический",
            "issue": 1990,
            "eng_volume": 12.0,
            "color": "Белый",
            "body_type": "Туристический",
            "milage": "Не указано",
            "price": 13000.0
        },
        {
            "id": "25325240",
            "mark": "Mercedes-Benz",
            "model": "Mercedes-Benz Туристический",
            "issue": 2007,
            "eng_volume": 3.0,
            "color": "Черный",
            "body_type": "Туристический",
            "milage": 571000,
            "price": 30000.0
        },
        {
            "id": "25340614",
            "mark": "Mercedes-Benz",
            "model": "Mercedes-Benz Междугородный",
            "issue": 2017,
            "eng_volume": 2.7,
            "color": "Белый",
            "body_type": "Междугородный",
            "milage": 450000,
            "price": 22000.0
        },
        {
            "id": "25353832",
            "mark": "Ford",
            "model": "Ford Transit",
            "issue": 2005,
            "eng_volume": 20.0,
            "color": "Синий",
            "body_type": "Междугородный",
            "milage": "Не указано",
            "price": 5500.0
        },
        {
            "id": "25366588",
            "mark": "Mercedes-Benz",
            "model": "Mercedes-Benz Пригородный",
            "issue": 2003,
            "eng_volume": 2.2,
            "color": "Белый",
            "body_type": "Пригородный",
            "milage": 245000,
            "price": 9800.0
        },
        {
            "id": "25377903",
            "mark": "Neoplan",
            "model": "Neoplan Cityliner",
            "issue": 1999,
            "eng_volume": 12.0,
            "color": "Белый",
            "body_type": "Туристический",
            "milage": 500000,
            "price": 18206.0
        },
        {
            "id": "27038829",
            "mark": "1",
            "model": "1",
            "issue": 1,
            "eng_volume": 1.0,
            "color": "1",
            "body_type": "Cедан",
            "milage": 1,
            "price": 1.0
        },
        {
            "id": "30204735",
            "mark": "Mercedes-Benz",
            "model": "Mercedes-Benz Междугородный",
            "issue": 2012,
            "eng_volume": 2.2,
            "color": "Белый",
            "body_type": "Междугородный",
            "milage": 412000,
            "price": 17000.0
        },
        {
            "id": "30215986",
            "mark": "Mercedes-Benz",
            "model": "Mercedes-Benz Пригородный",
            "issue": 2000,
            "eng_volume": 3.0,
            "color": "Белый",
            "body_type": "Пригородный",
            "milage": 415000,
            "price": 7500.0
        },
        {
            "id": "30230627",
            "mark": "Mercedes-Benz",
            "model": "Mercedes-Benz Междугородный",
            "issue": 2003,
            "eng_volume": 2.2,
            "color": "Серебристый",
            "body_type": "Междугородный",
            "milage": 417000,
            "price": 7500.0
        },
        {
            "id": "30244949",
            "mark": "Mercedes-Benz",
            "model": "Mercedes-Benz Междугородный",
            "issue": 2005,
            "eng_volume": 2.2,
            "color": "Серебристый",
            "body_type": "Междугородный",
            "milage": 325000,
            "price": 13500.0
        },
        {
            "id": "30259889",
            "mark": "Mercedes-Benz",
            "model": "Mercedes-Benz Междугородный",
            "issue": 2011,
            "eng_volume": 2.2,
            "color": "Белый",
            "body_type": "Междугородный",
            "milage": "Не указано",
            "price": 15172.0
        },
        {
            "id": "30275092",
            "mark": "Mercedes-Benz",
            "model": "Mercedes-Benz Городской",
            "issue": 1991,
            "eng_volume": 3.0,
            "color": "Белый",
            "body_type": "Городской",
            "milage": 317000,
            "price": 4248.0
        },
        {
            "id": "30289108",
            "mark": "Mercedes-Benz",
            "model": "Mercedes-Benz Туристический",
            "issue": 2003,
            "eng_volume": 2.2,
            "color": "Белый",
            "body_type": "Туристический",
            "milage": "Не указано",
            "price": 12800.0
        },
        {
            "id": "30302496",
            "mark": "Mercedes-Benz",
            "model": "Mercedes-Benz Туристический",
            "issue": 2005,
            "eng_volume": 2.2,
            "color": "Белый",
            "body_type": "Туристический",
            "milage": "Не указано",
            "price": 8496.0
        },
        {
            "id": "30316635",
            "mark": "Setra",
            "model": "Setra Top Class",
            "issue": 1984,
            "eng_volume": 4.0,
            "color": "Жёлтый",
            "body_type": "Туристический",
            "milage": "Не указано",
            "price": 10000.0
        },
        {
            "id": "30331046",
            "mark": "Scania",
            "model": "Scania Туристический",
            "issue": 1990,
            "eng_volume": 12.0,
            "color": "Белый",
            "body_type": "Туристический",
            "milage": "Не указано",
            "price": 13000.0
        },
        {
            "id": "30343715",
            "mark": "Mercedes-Benz",
            "model": "Mercedes-Benz Туристический",
            "issue": 2007,
            "eng_volume": 3.0,
            "color": "Черный",
            "body_type": "Туристический",
            "milage": 571000,
            "price": 30000.0
        },
        {
            "id": "30359635",
            "mark": "Mercedes-Benz",
            "model": "Mercedes-Benz Междугородный",
            "issue": 2017,
            "eng_volume": 2.7,
            "color": "Белый",
            "body_type": "Междугородный",
            "milage": 450000,
            "price": 22000.0
        },
        {
            "id": "30373009",
            "mark": "Ford",
            "model": "Ford Transit",
            "issue": 2005,
            "eng_volume": 20.0,
            "color": "Синий",
            "body_type": "Междугородный",
            "milage": "Не указано",
            "price": 5500.0
        },
        {
            "id": "30388317",
            "mark": "Mercedes-Benz",
            "model": "Mercedes-Benz Пригородный",
            "issue": 2003,
            "eng_volume": 2.2,
            "color": "Белый",
            "body_type": "Пригородный",
            "milage": 245000,
            "price": 9800.0
        },
        {
            "id": "30401191",
            "mark": "Neoplan",
            "model": "Neoplan Cityliner",
            "issue": 1999,
            "eng_volume": 12.0,
            "color": "Белый",
            "body_type": "Туристический",
            "milage": 500000,
            "price": 18206.0
        },
        {
            "id": "35042126",
            "mark": "Mercedes-Benz",
            "model": "Mercedes-Benz Междугородный",
            "issue": 2012,
            "eng_volume": 2.2,
            "color": "Белый",
            "body_type": "Междугородный",
            "milage": 412000,
            "price": 17000.0
        },
        {
            "id": "35054904",
            "mark": "Mercedes-Benz",
            "model": "Mercedes-Benz Пригородный",
            "issue": 2000,
            "eng_volume": 3.0,
            "color": "Белый",
            "body_type": "Пригородный",
            "milage": 415000,
            "price": 7500.0
        },
        {
            "id": "35067807",
            "mark": "Mercedes-Benz",
            "model": "Mercedes-Benz Междугородный",
            "issue": 2003,
            "eng_volume": 2.2,
            "color": "Серебристый",
            "body_type": "Междугородный",
            "milage": 417000,
            "price": 7500.0
        },
        {
            "id": "35083581",
            "mark": "Mercedes-Benz",
            "model": "Mercedes-Benz Междугородный",
            "issue": 2005,
            "eng_volume": 2.2,
            "color": "Серебристый",
            "body_type": "Междугородный",
            "milage": 325000,
            "price": 13500.0
        },
        {
            "id": "35097898",
            "mark": "Mercedes-Benz",
            "model": "Mercedes-Benz Междугородный",
            "issue": 2011,
            "eng_volume": 2.2,
            "color": "Белый",
            "body_type": "Междугородный",
            "milage": "Не указано",
            "price": 15172.0
        },
        {
            "id": "35111427",
            "mark": "Mercedes-Benz",
            "model": "Mercedes-Benz Городской",
            "issue": 1991,
            "eng_volume": 3.0,
            "color": "Белый",
            "body_type": "Городской",
            "milage": 317000,
            "price": 4248.0
        },
        {
            "id": "35129534",
            "mark": "Mercedes-Benz",
            "model": "Mercedes-Benz Туристический",
            "issue": 2003,
            "eng_volume": 2.2,
            "color": "Белый",
            "body_type": "Туристический",
            "milage": "Не указано",
            "price": 12800.0
        },
        {
            "id": "35143891",
            "mark": "Mercedes-Benz",
            "model": "Mercedes-Benz Туристический",
            "issue": 2005,
            "eng_volume": 2.2,
            "color": "Белый",
            "body_type": "Туристический",
            "milage": "Не указано",
            "price": 8496.0
        },
        {
            "id": "35158219",
            "mark": "Setra",
            "model": "Setra Top Class",
            "issue": 1984,
            "eng_volume": 4.0,
            "color": "Жёлтый",
            "body_type": "Туристический",
            "milage": "Не указано",
            "price": 10000.0
        },
        {
            "id": "35172553",
            "mark": "Scania",
            "model": "Scania Туристический",
            "issue": 1990,
            "eng_volume": 12.0,
            "color": "Белый",
            "body_type": "Туристический",
            "milage": "Не указано",
            "price": 13000.0
        },
        {
            "id": "35186244",
            "mark": "Mercedes-Benz",
            "model": "Mercedes-Benz Туристический",
            "issue": 2007,
            "eng_volume": 3.0,
            "color": "Черный",
            "body_type": "Туристический",
            "milage": 571000,
            "price": 30000.0
        },
        {
            "id": "35200228",
            "mark": "Mercedes-Benz",
            "model": "Mercedes-Benz Междугородный",
            "issue": 2017,
            "eng_volume": 2.7,
            "color": "Белый",
            "body_type": "Междугородный",
            "milage": 450000,
            "price": 22000.0
        },
        {
            "id": "35214572",
            "mark": "Ford",
            "model": "Ford Transit",
            "issue": 2005,
            "eng_volume": 20.0,
            "color": "Синий",
            "body_type": "Междугородный",
            "milage": "Не указано",
            "price": 5500.0
        },
        {
            "id": "35229865",
            "mark": "Mercedes-Benz",
            "model": "Mercedes-Benz Пригородный",
            "issue": 2003,
            "eng_volume": 2.2,
            "color": "Белый",
            "body_type": "Пригородный",
            "milage": 245000,
            "price": 9800.0
        },
        {
            "id": "35245344",
            "mark": "Neoplan",
            "model": "Neoplan Cityliner",
            "issue": 1999,
            "eng_volume": 12.0,
            "color": "Белый",
            "body_type": "Туристический",
            "milage": 500000,
            "price": 18206.0
        },
        {
            "id": "37034117",
            "mark": "Mercedes-Benz",
            "model": "Mercedes-Benz Междугородный",
            "issue": 2012,
            "eng_volume": 2.2,
            "color": "Белый",
            "body_type": "Междугородный",
            "milage": 412000,
            "price": 17000.0
        },
        {
            "id": "37050763",
            "mark": "Mercedes-Benz",
            "model": "Mercedes-Benz Пригородный",
            "issue": 2000,
            "eng_volume": 3.0,
            "color": "Белый",
            "body_type": "Пригородный",
            "milage": 415000,
            "price": 7500.0
        },
        {
            "id": "37064163",
            "mark": "Mercedes-Benz",
            "model": "Mercedes-Benz Междугородный",
            "issue": 2003,
            "eng_volume": 2.2,
            "color": "Серебристый",
            "body_type": "Междугородный",
            "milage": 417000,
            "price": 7500.0
        },
        {
            "id": "37076673",
            "mark": "Mercedes-Benz",
            "model": "Mercedes-Benz Междугородный",
            "issue": 2005,
            "eng_volume": 2.2,
            "color": "Серебристый",
            "body_type": "Междугородный",
            "milage": 325000,
            "price": 13500.0
        },
        {
            "id": "37091156",
            "mark": "Mercedes-Benz",
            "model": "Mercedes-Benz Междугородный",
            "issue": 2011,
            "eng_volume": 2.2,
            "color": "Белый",
            "body_type": "Междугородный",
            "milage": "Не указано",
            "price": 15172.0
        },
        {
            "id": "37103041",
            "mark": "Mercedes-Benz",
            "model": "Mercedes-Benz Городской",
            "issue": 1991,
            "eng_volume": 3.0,
            "color": "Белый",
            "body_type": "Городской",
            "milage": 317000,
            "price": 4248.0
        },
        {
            "id": "37118401",
            "mark": "Mercedes-Benz",
            "model": "Mercedes-Benz Туристический",
            "issue": 2003,
            "eng_volume": 2.2,
            "color": "Белый",
            "body_type": "Туристический",
            "milage": "Не указано",
            "price": 12800.0
        },
        {
            "id": "37132772",
            "mark": "Mercedes-Benz",
            "model": "Mercedes-Benz Туристический",
            "issue": 2005,
            "eng_volume": 2.2,
            "color": "Белый",
            "body_type": "Туристический",
            "milage": "Не указано",
            "price": 8496.0
        },
        {
            "id": "37146336",
            "mark": "Setra",
            "model": "Setra Top Class",
            "issue": 1984,
            "eng_volume": 4.0,
            "color": "Жёлтый",
            "body_type": "Туристический",
            "milage": "Не указано",
            "price": 10000.0
        },
        {
            "id": "37160322",
            "mark": "Scania",
            "model": "Scania Туристический",
            "issue": 1990,
            "eng_volume": 12.0,
            "color": "Белый",
            "body_type": "Туристический",
            "milage": "Не указано",
            "price": 13000.0
        },
        {
            "id": "37174693",
            "mark": "Mercedes-Benz",
            "model": "Mercedes-Benz Туристический",
            "issue": 2007,
            "eng_volume": 3.0,
            "color": "Черный",
            "body_type": "Туристический",
            "milage": 571000,
            "price": 30000.0
        },
        {
            "id": "37189092",
            "mark": "Mercedes-Benz",
            "model": "Mercedes-Benz Междугородный",
            "issue": 2017,
            "eng_volume": 2.7,
            "color": "Белый",
            "body_type": "Междугородный",
            "milage": 450000,
            "price": 22000.0
        },
        {
            "id": "37203351",
            "mark": "Ford",
            "model": "Ford Transit",
            "issue": 2005,
            "eng_volume": 20.0,
            "color": "Синий",
            "body_type": "Междугородный",
            "milage": "Не указано",
            "price": 5500.0
        },
        {
            "id": "37218707",
            "mark": "Mercedes-Benz",
            "model": "Mercedes-Benz Пригородный",
            "issue": 2003,
            "eng_volume": 2.2,
            "color": "Белый",
            "body_type": "Пригородный",
            "milage": 245000,
            "price": 9800.0
        },
        {
            "id": "37235098",
            "mark": "Neoplan",
            "model": "Neoplan Cityliner",
            "issue": 1999,
            "eng_volume": 12.0,
            "color": "Белый",
            "body_type": "Туристический",
            "milage": 500000,
            "price": 18206.0
        }
    ],
    "cars_counter": 61
}